finic_py/__init__.py
finic_py/cli.py
finic_py/copilot.py
finic_py/finic.py
finic_py/test.py
finic_py-0.1.52.dist-info/METADATA
finic_py-0.1.52.dist-info/WHEEL
finic_py-0.1.52.dist-info/entry_points.txt
finic_py-0.1.52.dist-info/RECORD
