Metadata-Version: 2.1
Name: finic-py
Version: 0.1.52
Summary: Finic.ai is a platform for building and deploying browser automations. This is the Python client for Finic
Author: Ayan Bandyopadhyay
Author-email: ayan@finic.ai
Requires-Python: >=3.10,<4.0
Classifier: Programming Language :: Python :: 3
Classifier: Programming Language :: Python :: 3.10
Classifier: Programming Language :: Python :: 3.11
Classifier: Programming Language :: Python :: 3.12
Requires-Dist: datetime (>=5.5,<6.0)
Requires-Dist: playwright (==1.47.0)
Requires-Dist: pydantic (>=2.9.1,<3.0.0)
Requires-Dist: python-dotenv (>=1.0.1,<2.0.0)
Requires-Dist: pyyaml (>=6.0.2,<7.0.0)
Requires-Dist: requests (>=2.32.3,<3.0.0)
